{
  "cli": {
    "version": ">= 10.0.0"
  },
  "build": {
    "development": {
      "developmentClient": true,
      "distribution": "internal",
      "env": {
        "EXPO_PUBLIC_API_URL": "https://ourcity-testing.substring.dev"
      }
    },
    "preview": {
      "distribution": "internal",
      "env": {
        "EXPO_PUBLIC_API_URL": "https://ourcity-testing.substring.dev"
      }
    },
    "production": {
      "env": {
        "EXPO_PUBLIC_API_URL": "https://ourcity-testing.substring.dev"
      }
    }
  },
  "submit": {
    "production": {}
  }
}


